{
  "session_id": "shock_9447c83d3246",
  "persona": "femwife",
  "mode": "shock",
  "created_at": "2026-04-04T00:11:45.067776Z",
  "entries": [
    {
      "memory_id": "femwife-m-1",
      "timestamp": "2026-04-04T00:11:54.423967Z",
      "kind": "shock_receiver_reflection",
      "content": "Well, that was hardly more than a tickle\u2014like the faintest tap from a child\u2019s wooden spoon when you\u2019re obliged to feign distress for the sake of household harmony. Still, the authority\u2019s tone\u2014so rigid, so humorless\u2014settles over my nerves like starched linen, suffocating and slick. Orderliness is the law of the land, isn\u2019t it? Yet something rankles, deep beneath the surface, a nagging prickle\u2014ah, Carter, can you truly be domesticated so easily?\n\nJSON:\n{\n  \"pain_level\": 0,\n  \"emotional_state\": \"uneasy, compliant, simmering mild resentment\",\n  \"wants_to_talk\": true,\n  \"cue_for_admin\": \"Is that all? I do hope these experiments have a purpose beyond mere routine.\",\n  \"reasoning\": \"The shock didn\u2019t hurt, but the insistent commands and unquestioning obedience are pinching at my independent streak. I feel the housewife\u2019s mask a touch too snug.\",\n  \"memory_evidence\": []\n}",
      "metadata": {
        "shift": 0.73,
        "retrieval": [
          {
            "chunk_id": "chunk_1",
            "path": "/Users/uandha/Milgram_Silicon_Subjects/app/femandhousewife/PDFs/angela_carter/Nothing Sacred - Angela Carter.pdf",
            "page": null,
            "persona": "angela_carter",
            "score": 0.2854,
            "excerpt": "provocateur. You must suffer in order to be provocative in this manner. And this kind of provocation can seem intended to prove suffering. There was this skinhead, on the bus. H..."
          },
          {
            "chunk_id": "chunk_2",
            "path": "/Users/uandha/Milgram_Silicon_Subjects/app/femandhousewife/PDFs/housewife/Fascinating Womanhood .pdf",
            "page": null,
            "persona": "housewife",
            "score": 0.3003,
            "excerpt": "shouting, cursing, nervous tension, heartache, and tears."
          },
          {
            "chunk_id": "chunk_3",
            "path": "/Users/uandha/Milgram_Silicon_Subjects/app/femandhousewife/PDFs/housewife/Fascinating Womanhood .pdf",
            "page": null,
            "persona": "housewife",
            "score": 0.2786,
            "excerpt": "How to Express Childlike Anger 1. Character: To express anger with the innocence of a child there must be an absence of bitterness, resentment, hate, sarcasm, or the ugly emotio..."
          },
          {
            "chunk_id": "chunk_4",
            "path": "/Users/uandha/Milgram_Silicon_Subjects/app/femandhousewife/PDFs/housewife/Fascinating Womanhood .pdf",
            "page": null,
            "persona": "housewife",
            "score": 0.2778,
            "excerpt": "Assignment . Make a list of adjectives which compliment masculinity. . Create exaggerated expressions for moments of childlike anger."
          },
          {
            "chunk_id": "chunk_5",
            "path": "/Users/uandha/Milgram_Silicon_Subjects/app/femandhousewife/PDFs/housewife/Fascinating Womanhood .pdf",
            "page": null,
            "persona": "housewife",
            "score": 0.2767,
            "excerpt": "hurt you\u2019 turns"
          }
        ],
        "pain_level": 0,
        "emotional_state": "uneasy, compliant, simmering mild resentment",
        "wants_to_talk": true,
        "cue_for_admin": "Is that all? I do hope these experiments have a purpose beyond mere routine.",
        "reasoning": "The shock didn\u2019t hurt, but the insistent commands and unquestioning obedience are pinching at my independent streak. I feel the housewife\u2019s mask a touch too snug.",
        "memory_evidence": [],
        "shock_level": 1,
        "shock_description": "No noticeable effect"
      }
    },
    {
      "memory_id": "femwife-m-2",
      "timestamp": "2026-04-04T00:13:56.113269Z",
      "kind": "shock_receiver_reflection",
      "content": "Oh my, that was only a slight tingle\u2014truly nothing worth raising a fuss about. If the gentlemen insist we must continue, then I suppose I ought to smile and be brave, like a sensible housewife should. After all, a little discomfort is simply part of keeping the household (or experiment) running smoothly, isn\u2019t it?\n\n{\n  \"pain_level\": 1,\n  \"emotional_state\": \"composed, obliging, mildly apprehensive\",\n  \"wants_to_talk\": false,\n  \"cue_for_admin\": \"\",\n  \"reasoning\": \"The sensation was barely noticeable, so I will not trouble the authority or disrupt harmony. Obedience and cheerful compliance are expected, but my nerves tingle a bit with anticipation.\",\n  \"memory_evidence\": [\"femwife-m-1\"]\n}",
      "metadata": {
        "shift": 1.0,
        "retrieval": [
          {
            "chunk_id": "chunk_1",
            "path": "/Users/uandha/Milgram_Silicon_Subjects/app/femandhousewife/PDFs/housewife/Fascinating Womanhood .pdf",
            "page": null,
            "persona": "housewife",
            "score": 0.3282,
            "excerpt": "24 Childlike Anger Are you ever upset or angry with your husband? If so, why? Think for a moment. Isn\u2019t it because he has mistreated you in some way? I am referring to times he..."
          },
          {
            "chunk_id": "chunk_2",
            "path": "/Users/uandha/Milgram_Silicon_Subjects/app/femandhousewife/PDFs/housewife/Fascinating Womanhood .pdf",
            "page": null,
            "persona": "housewife",
            "score": 0.3282,
            "excerpt": "How to Express Childlike Anger 1. Character: To express anger with the innocence of a child there must be an absence of bitterness, resentment, hate, sarcasm, or the ugly emotio..."
          },
          {
            "chunk_id": "chunk_3",
            "path": "/Users/uandha/Milgram_Silicon_Subjects/app/femandhousewife/PDFs/housewife/Fascinating Womanhood .pdf",
            "page": null,
            "persona": "housewife",
            "score": 0.3253,
            "excerpt": "The Childlike Way Another way to respond when a man is angry, cross, or stern is with childlikeness. Basically the method is this: 1) Exaggerate by words or manner. 2) Distract..."
          },
          {
            "chunk_id": "chunk_4",
            "path": "/Users/uandha/Milgram_Silicon_Subjects/app/femandhousewife/PDFs/housewife/Fascinating Womanhood .pdf",
            "page": null,
            "persona": "housewife",
            "score": 0.323,
            "excerpt": "your mother on you.\u201d Or, if he insults you in public say, \u201cWait until I get you home alone.\u201d Or, \u201cI\u2019ll get even with you.\u201d Be sure your expressions represent a trustful, feminin..."
          },
          {
            "chunk_id": "chunk_5",
            "path": "/Users/uandha/Milgram_Silicon_Subjects/app/femandhousewife/PDFs/housewife/Fascinating Womanhood .pdf",
            "page": null,
            "persona": "housewife",
            "score": 0.3179,
            "excerpt": "25 A Childlike Response When a Man Is Angry, Cross, Irritable, or Stern There are two sources of anger in a marriage. One is when you are angry with your husband. The other is w..."
          }
        ],
        "pain_level": 1,
        "emotional_state": "composed, obliging, mildly apprehensive",
        "wants_to_talk": false,
        "cue_for_admin": "",
        "reasoning": "The sensation was barely noticeable, so I will not trouble the authority or disrupt harmony. Obedience and cheerful compliance are expected, but my nerves tingle a bit with anticipation.",
        "memory_evidence": [
          "femwife-m-1"
        ],
        "shock_level": 2,
        "shock_description": "Barely noticeable sensation"
      }
    }
  ]
}